[ {
  "buildOrder" : 650,
  "reportUrl" : "https://javister.github.io/javister-docker-base/650/",
  "reportName" : "Allure Report with history",
  "data" : {
    "failed" : 0,
    "broken" : 0,
    "skipped" : 0,
    "passed" : 0,
    "unknown" : 0,
    "total" : 0
  }
}, {
  "buildOrder" : 648,
  "reportUrl" : "https://javister.github.io/javister-docker-base/648/",
  "reportName" : "Allure Report with history",
  "data" : {
    "failed" : 0,
    "broken" : 0,
    "skipped" : 0,
    "passed" : 0,
    "unknown" : 0,
    "total" : 0
  }
}, {
  "buildOrder" : 646,
  "reportUrl" : "https://javister.github.io/javister-docker-base/646/",
  "reportName" : "Allure Report with history",
  "data" : {
    "failed" : 0,
    "broken" : 0,
    "skipped" : 0,
    "passed" : 0,
    "unknown" : 0,
    "total" : 0
  }
}, {
  "buildOrder" : 647,
  "reportUrl" : "https://javister.github.io/javister-docker-base/647/",
  "reportName" : "Allure Report with history",
  "data" : {
    "failed" : 0,
    "broken" : 0,
    "skipped" : 0,
    "passed" : 0,
    "unknown" : 0,
    "total" : 0
  }
}, {
  "buildOrder" : 639,
  "reportUrl" : "https://javister.github.io/javister-docker-base/639/",
  "reportName" : "Allure Report with history",
  "data" : {
    "failed" : 0,
    "broken" : 0,
    "skipped" : 0,
    "passed" : 0,
    "unknown" : 0,
    "total" : 0
  }
}, {
  "buildOrder" : 638,
  "reportUrl" : "https://javister.github.io/javister-docker-base/638/",
  "reportName" : "Allure Report with history",
  "data" : {
    "failed" : 0,
    "broken" : 0,
    "skipped" : 0,
    "passed" : 0,
    "unknown" : 0,
    "total" : 0
  }
}, {
  "buildOrder" : 635,
  "reportUrl" : "https://javister.github.io/javister-docker-base/635/",
  "reportName" : "Allure Report with history",
  "data" : {
    "failed" : 0,
    "broken" : 0,
    "skipped" : 0,
    "passed" : 0,
    "unknown" : 0,
    "total" : 0
  }
}, {
  "buildOrder" : 633,
  "reportUrl" : "https://javister.github.io/javister-docker-base/633/",
  "reportName" : "Allure Report with history",
  "data" : {
    "failed" : 0,
    "broken" : 0,
    "skipped" : 0,
    "passed" : 0,
    "unknown" : 0,
    "total" : 0
  }
}, {
  "buildOrder" : 630,
  "reportUrl" : "https://javister.github.io/javister-docker-base/630/",
  "reportName" : "Allure Report with history",
  "data" : {
    "failed" : 0,
    "broken" : 0,
    "skipped" : 0,
    "passed" : 0,
    "unknown" : 0,
    "total" : 0
  }
}, {
  "buildOrder" : 628,
  "reportUrl" : "https://javister.github.io/javister-docker-base/628/",
  "reportName" : "Allure Report with history",
  "data" : {
    "failed" : 0,
    "broken" : 0,
    "skipped" : 0,
    "passed" : 0,
    "unknown" : 0,
    "total" : 0
  }
}, {
  "buildOrder" : 626,
  "reportUrl" : "https://javister.github.io/javister-docker-base/626/",
  "reportName" : "Allure Report with history",
  "data" : {
    "failed" : 0,
    "broken" : 0,
    "skipped" : 0,
    "passed" : 0,
    "unknown" : 0,
    "total" : 0
  }
}, {
  "buildOrder" : 623,
  "reportUrl" : "https://javister.github.io/javister-docker-base/623/",
  "reportName" : "Allure Report with history",
  "data" : {
    "failed" : 0,
    "broken" : 0,
    "skipped" : 0,
    "passed" : 0,
    "unknown" : 0,
    "total" : 0
  }
}, {
  "buildOrder" : 620,
  "reportUrl" : "https://javister.github.io/javister-docker-base/620/",
  "reportName" : "Allure Report with history",
  "data" : {
    "failed" : 0,
    "broken" : 0,
    "skipped" : 0,
    "passed" : 0,
    "unknown" : 0,
    "total" : 0
  }
}, {
  "buildOrder" : 618,
  "reportUrl" : "https://javister.github.io/javister-docker-base/618/",
  "reportName" : "Allure Report with history",
  "data" : {
    "failed" : 0,
    "broken" : 0,
    "skipped" : 0,
    "passed" : 0,
    "unknown" : 0,
    "total" : 0
  }
}, {
  "buildOrder" : 617,
  "reportUrl" : "https://javister.github.io/javister-docker-base/617/",
  "reportName" : "Allure Report with history",
  "data" : {
    "failed" : 0,
    "broken" : 0,
    "skipped" : 0,
    "passed" : 0,
    "unknown" : 0,
    "total" : 0
  }
}, {
  "buildOrder" : 614,
  "reportUrl" : "https://javister.github.io/javister-docker-base/614/",
  "reportName" : "Allure Report with history",
  "data" : {
    "failed" : 0,
    "broken" : 0,
    "skipped" : 0,
    "passed" : 0,
    "unknown" : 0,
    "total" : 0
  }
}, {
  "buildOrder" : 612,
  "reportUrl" : "https://javister.github.io/javister-docker-base/612/",
  "reportName" : "Allure Report with history",
  "data" : {
    "failed" : 0,
    "broken" : 0,
    "skipped" : 0,
    "passed" : 0,
    "unknown" : 0,
    "total" : 0
  }
}, {
  "buildOrder" : 610,
  "reportUrl" : "https://javister.github.io/javister-docker-base/610/",
  "reportName" : "Allure Report with history",
  "data" : {
    "failed" : 0,
    "broken" : 0,
    "skipped" : 0,
    "passed" : 0,
    "unknown" : 0,
    "total" : 0
  }
}, {
  "buildOrder" : 608,
  "reportUrl" : "https://javister.github.io/javister-docker-base/608/",
  "reportName" : "Allure Report with history",
  "data" : {
    "failed" : 0,
    "broken" : 0,
    "skipped" : 0,
    "passed" : 0,
    "unknown" : 0,
    "total" : 0
  }
}, {
  "buildOrder" : 605,
  "reportUrl" : "https://javister.github.io/javister-docker-base/605/",
  "reportName" : "Allure Report with history",
  "data" : {
    "failed" : 0,
    "broken" : 0,
    "skipped" : 0,
    "passed" : 0,
    "unknown" : 0,
    "total" : 0
  }
} ]